main.py
tuning_fork_cli-2.dist-info/METADATA
tuning_fork_cli-2.dist-info/RECORD
tuning_fork_cli-2.dist-info/WHEEL
tuning_fork_cli-2.dist-info/entry_points.txt
tuning_fork_cli-2.dist-info/top_level.txt
