Metadata-Version: 2.1
Name: tuning-fork-cli
Version: 2
Summary: CLI for tuning_fork
Home-page: https://github.com/ddxtanx/TuningFork
Author: Garrett Credi
Author-email: gcc@ameritech.net
License: UNKNOWN
Platform: UNKNOWN
Classifier: Programming Language :: Python :: 3
Classifier: License :: OSI Approved :: MIT License
Classifier: Operating System :: OS Independent
Requires-Dist: tuning-fork
